hakoniwa_pdu/pdu_manager.py
hakoniwa_pdu/apps/drone/__init__.py
hakoniwa_pdu/apps/drone/hako_drone_service.py
hakoniwa_pdu/apps/drone/hakosim.py
hakoniwa_pdu/apps/drone/hakosim_lidar.py
hakoniwa_pdu/apps/drone/hakosim_types.py
hakoniwa_pdu/apps/launcher/__init__.py
hakoniwa_pdu/apps/launcher/effective_model.py
hakoniwa_pdu/apps/launcher/envmerge.py
hakoniwa_pdu/apps/launcher/hako_asset_runner.py
hakoniwa_pdu/apps/launcher/hako_cli.py
hakoniwa_pdu/apps/launcher/hako_launcher.py
hakoniwa_pdu/apps/launcher/hako_monitor.py
hakoniwa_pdu/apps/launcher/loader.py
hakoniwa_pdu/apps/launcher/model.py
hakoniwa_pdu/apps/launcher/schemas/launcher.schema.json
hakoniwa_pdu/apps/mcp/hako_mcp_base_server.py
hakoniwa_pdu/apps/mcp/hako_mcp_drone_server.py
hakoniwa_pdu/apps/mcp/server.py
hakoniwa_pdu/apps/rpcserver/__init__.py
hakoniwa_pdu/apps/rpcserver/hako_base_rpc_server.py
hakoniwa_pdu/apps/rpcserver/hako_drone_rpc_server.py
hakoniwa_pdu/apps/rpcserver/server_rpc.py
hakoniwa_pdu/impl/__init__.py
hakoniwa_pdu/impl/communication_buffer.py
hakoniwa_pdu/impl/data_packet.py
hakoniwa_pdu/impl/icommunication_service.py
hakoniwa_pdu/impl/pdu_channel_config.py
hakoniwa_pdu/impl/pdu_convertor.py
hakoniwa_pdu/impl/shm_communication_service.py
hakoniwa_pdu/impl/websocket_base_communication_service.py
hakoniwa_pdu/impl/websocket_communication_service.py
hakoniwa_pdu/impl/websocket_server_communication_service.py
hakoniwa_pdu/impl/hako_binary/__init__.py
hakoniwa_pdu/impl/hako_binary/binary_io.py
hakoniwa_pdu/impl/hako_binary/binary_reader.py
hakoniwa_pdu/impl/hako_binary/binary_writer.py
hakoniwa_pdu/impl/hako_binary/offset_map.py
hakoniwa_pdu/impl/hako_binary/offset_parser.py
hakoniwa_pdu/pdu_msgs/__init__.py
hakoniwa_pdu/pdu_msgs/binary_io.py
hakoniwa_pdu/pdu_msgs/pdu_utils.py
hakoniwa_pdu/pdu_msgs/builtin_interfaces/__init__.py
hakoniwa_pdu/pdu_msgs/builtin_interfaces/pdu_conv_Time.py
hakoniwa_pdu/pdu_msgs/builtin_interfaces/pdu_pytype_Time.py
hakoniwa_pdu/pdu_msgs/can_msgs/__init__.py
hakoniwa_pdu-1.3.5.dist-info/licenses/LICENSE
hakoniwa_pdu-1.3.5.dist-info/METADATA
hakoniwa_pdu-1.3.5.dist-info/WHEEL
hakoniwa_pdu-1.3.5.dist-info/top_level.txt
hakoniwa_pdu-1.3.5.dist-info/RECORD
