Metadata-Version: 2.4
Name: hakoniwa-pdu
Version: 1.3.5
Summary: Hakoniwa PDU communication library for Python
Author-email: Takashi Mori <tmori@hakoniwa-lab.net>
Project-URL: Homepage, https://github.com/hakoniwalab
Project-URL: Repository, https://github.com/hakoniwalab/hakoniwa-pdu-python
License-File: LICENSE
Requires-Dist: websockets>=11.0
Requires-Dist: jsonschema>=4.23.0
Requires-Dist: pydantic>=2.7.0
Requires-Dist: mcp==1.0.0
Provides-Extra: test
Requires-Dist: pytest; extra == "test"
Requires-Dist: pytest-asyncio; extra == "test"
Dynamic: license-file
